bbclient/__init__.py
bbclient/bbclient.py
bbclient/bbcommon.py
bbclient/bbevent.py
bbclient/console.py
tests/__init__.py
tests/test.py
tests/command_tests/__init__.py
tests/command_tests/common.py
tests/command_tests/test_all_providers.py
tests/command_tests/test_build_file.py
tests/command_tests/test_build_targets.py
tests/command_tests/test_client_complete.py
tests/command_tests/test_compare_revisions.py
tests/command_tests/test_data_store_connector_cmd.py
tests/command_tests/test_data_store_connector_inc_hist_cmd.py
tests/command_tests/test_data_store_connector_release.py
tests/command_tests/test_data_store_connector_var_hist_cmd_emit.py
tests/command_tests/test_data_store_connector_varhist_cmd.py
tests/command_tests/test_disable_data_tracking.py
tests/command_tests/test_enable_data_tracking.py
tests/command_tests/test_find_best_provider.py
tests/command_tests/test_find_config_file_path.py
tests/command_tests/test_find_config_files.py
tests/command_tests/test_find_files_matching_in_dir.py
tests/command_tests/test_find_providers.py
tests/command_tests/test_find_sigInfo.py
tests/command_tests/test_generate_dep_tree_event.py
tests/command_tests/test_generate_dot_graph.py
tests/command_tests/test_generate_targets_tree.py
tests/command_tests/test_get_all_appends.py
tests/command_tests/test_get_all_keys_with_flags.py
tests/command_tests/test_get_bb_file_priority.py
tests/command_tests/test_get_default_preference.py
tests/command_tests/test_get_file_appends.py
tests/command_tests/test_get_layer_priorities.py
tests/command_tests/test_get_overlayed_recipes.py
tests/command_tests/test_get_r_providers.py
tests/command_tests/test_get_recipe_depends.py
tests/command_tests/test_get_recipe_inherits.py
tests/command_tests/test_get_recipe_packages.py
tests/command_tests/test_get_recipe_packages_dynamic.py
tests/command_tests/test_get_recipe_provides.py
tests/command_tests/test_get_recipe_versions.py
tests/command_tests/test_get_recipes.py
bbclient-0.8.0.dist-info/LICENSE
bbclient-0.8.0.dist-info/METADATA
bbclient-0.8.0.dist-info/WHEEL
bbclient-0.8.0.dist-info/entry_points.txt
bbclient-0.8.0.dist-info/top_level.txt
bbclient-0.8.0.dist-info/RECORD
