Metadata-Version: 2.1
Name: bbclient
Version: 0.8.0
Summary: bbclient provides utility commands for bitbake.
Home-page: https://github.com/AngryMane/bbclient
Author: AngryMane
Author-email: regulationdango@gmail.com
License: MIT
Keywords: yocto,bitbake
Platform: UNKNOWN
Classifier: Development Status :: 3 - Alpha
Classifier: Environment :: Plugins
Classifier: Topic :: Software Development :: Build Tools
Classifier: Intended Audience :: Developers
Classifier: Intended Audience :: Information Technology
Classifier: License :: OSI Approved :: MIT License
Classifier: Programming Language :: Python
Classifier: Programming Language :: Python :: 3 :: Only
Requires-Python: >=3.7
License-File: LICENSE
Requires-Dist: bbclient
